.gitignore
CHANGELOG.md
CMakeLists.txt
README.md
pyproject.toml
.devcontainer/Dockerfile
.devcontainer/devcontainer.json
.github/workflows/build_package.yml
.github/workflows/publish.yml
app/CMakeLists.txt
app/NeQuickG_JRC_exception.c
app/NeQuickG_JRC_exception.h
app/NeQuickG_JRC_input_data_std_stream.c
app/NeQuickG_JRC_input_data_std_stream.h
app/NeQuickG_JRC_input_data_stream.c
app/NeQuickG_JRC_input_data_stream.h
app/NeQuickG_JRC_main.c
ccir/ccir11.txt
ccir/ccir12.txt
ccir/ccir13.txt
ccir/ccir14.txt
ccir/ccir15.txt
ccir/ccir16.txt
ccir/ccir17.txt
ccir/ccir18.txt
ccir/ccir19.txt
ccir/ccir20.txt
ccir/ccir21.txt
ccir/ccir22.txt
doc/EC_logo.png
doc/doxy.cfg
lib/CMakeLists.txt
lib/ITU_R_P_371_8.c
lib/ITU_R_P_371_8.h
lib/NeQuickG_JRC.c
lib/NeQuickG_JRC_CCIR.h
lib/NeQuickG_JRC_Gauss_Kronrod_integration.c
lib/NeQuickG_JRC_Gauss_Kronrod_integration.h
lib/NeQuickG_JRC_MODIP.c
lib/NeQuickG_JRC_MODIP.h
lib/NeQuickG_JRC_MODIP_grid.c
lib/NeQuickG_JRC_MODIP_grid.h
lib/NeQuickG_JRC_TEC_integration.c
lib/NeQuickG_JRC_TEC_integration.h
lib/NeQuickG_JRC_context.h
lib/NeQuickG_JRC_coordinates.c
lib/NeQuickG_JRC_coordinates.h
lib/NeQuickG_JRC_electron_density.c
lib/NeQuickG_JRC_electron_density.h
lib/NeQuickG_JRC_geometry.c
lib/NeQuickG_JRC_geometry.h
lib/NeQuickG_JRC_input_data.c
lib/NeQuickG_JRC_input_data.h
lib/NeQuickG_JRC_interpolate.c
lib/NeQuickG_JRC_interpolate.h
lib/NeQuickG_JRC_iono_E_layer.c
lib/NeQuickG_JRC_iono_E_layer.h
lib/NeQuickG_JRC_iono_F1_layer.c
lib/NeQuickG_JRC_iono_F1_layer.h
lib/NeQuickG_JRC_iono_F2_layer.c
lib/NeQuickG_JRC_iono_F2_layer.h
lib/NeQuickG_JRC_iono_F2_layer_fourier_coefficients.c
lib/NeQuickG_JRC_iono_F2_layer_fourier_coefficients.h
lib/NeQuickG_JRC_iono_profile.c
lib/NeQuickG_JRC_iono_profile.h
lib/NeQuickG_JRC_iono_profile_types.h
lib/NeQuickG_JRC_math_utils.c
lib/NeQuickG_JRC_math_utils.h
lib/NeQuickG_JRC_ray.c
lib/NeQuickG_JRC_ray.h
lib/NeQuickG_JRC_ray_slant.c
lib/NeQuickG_JRC_ray_slant.h
lib/NeQuickG_JRC_ray_vertical.c
nequick.egg-info/PKG-INFO
nequick.egg-info/SOURCES.txt
nequick.egg-info/dependency_links.txt
nequick.egg-info/entry_points.txt
nequick.egg-info/requires.txt
nequick.egg-info/top_level.txt
