Metadata-Version: 2.4
Name: nequick
Version: 0.3.0
Summary: Package that wraps NeQuick in Python
Author-email: Miquel Garcia-Fernandez <miquel.garcia.fernandez@upc.edu>
License: MIT
Project-URL: Homepage, https://github.com/mgfernan/NeQuickJRC
Project-URL: Source, https://github.com/mgfernan/NeQuickJRC
Project-URL: Tracker, https://github.com/mgfernan/NeQuickJRC/issues
Requires-Python: >=3.9
Requires-Dist: numpy<2.0.0
Provides-Extra: test
Requires-Dist: coverage>=7.6.11; extra == "test"
Requires-Dist: pytest>=8.3.4; extra == "test"
Requires-Dist: pytest-env>=1.1.5; extra == "test"
Provides-Extra: release
Requires-Dist: python-semantic-release>=9.4.0; extra == "release"
